drugai/__init__.py
drugai/__main__.py
drugai/version.py
drugai/metrics/__init__.py
drugai-0.0.2.dist-info/LICENSE
drugai-0.0.2.dist-info/METADATA
drugai-0.0.2.dist-info/WHEEL
drugai-0.0.2.dist-info/entry_points.txt
drugai-0.0.2.dist-info/top_level.txt
drugai-0.0.2.dist-info/RECORD
