Metadata-Version: 2.1
Name: drugai
Version: 0.0.2
Summary: Pharmacy, medicine, chemistry and biology intersect with computers and AI 
Home-page: https://github.com/daiyizheng/drugai
Author: yizheng dai
Author-email: 387942239@qq.com
Maintainer: yizheng dai
Maintainer-email: 387942239@qq.com
License: Apache 2.0
Project-URL: Bug Reports, https://github.com/daiyizheng/drugai/issues
Project-URL: Source, https://github.com/daiyizheng/drugai
Keywords: Deep learning,Drug,Ai,Tool
Platform: any
Classifier: Intended Audience :: Developers
Classifier: License :: OSI Approved :: Apache Software License
Classifier: Programming Language :: Python
Classifier: Programming Language :: Python :: 3.7
Classifier: Programming Language :: Python :: 3.8
Classifier: Topic :: Software Development
Requires-Python: >=3.7
License-File: LICENSE
